lsst/__init__.py
lsst/rsp/__init__.py
lsst/rsp/_discovery.py
lsst/rsp/_exceptions.py
lsst/rsp/catalog.py
lsst/rsp/client.py
lsst/rsp/log.py
lsst/rsp/py.typed
lsst/rsp/service.py
lsst/rsp/utils.py
lsst/rsp/startup/__init__.py
lsst/rsp/startup/cli.py
lsst/rsp/startup/constants.py
lsst/rsp/startup/exceptions.py
lsst/rsp/startup/models/__init__.py
lsst/rsp/startup/models/noninteractive.py
lsst/rsp/startup/services/__init__.py
lsst/rsp/startup/services/labrunner/__init__.py
lsst/rsp/startup/services/labrunner/labrunner.py
lsst/rsp/startup/services/landing_page/__init__.py
lsst/rsp/startup/services/landing_page/exceptions.py
lsst/rsp/startup/services/landing_page/input.py
lsst/rsp/startup/services/landing_page/main.py
lsst/rsp/startup/services/landing_page/provisioner.py
lsst/rsp/startup/storage/__init__.py
lsst/rsp/startup/storage/command.py
lsst/rsp/startup/storage/logging.py
lsst_rsp-0.10.2.dist-info/licenses/LICENSE
lsst_rsp-0.10.2.dist-info/METADATA
lsst_rsp-0.10.2.dist-info/WHEEL
lsst_rsp-0.10.2.dist-info/entry_points.txt
lsst_rsp-0.10.2.dist-info/top_level.txt
lsst_rsp-0.10.2.dist-info/RECORD
