Metadata-Version: 2.4
Name: lsst-rsp
Version: 0.10.2
Summary: Utility functions for the Rubin Science Platform
Author-email: "Association of Universities for Research in Astronomy, Inc. (AURA)" <sqre-admin@lists.lsst.org>
License: MIT
Project-URL: Homepage, https://rsp.lsst.io/
Project-URL: Source, https://github.com/lsst-sqre/lsst-rsp
Keywords: rubin,lsst
Classifier: Development Status :: 4 - Beta
Classifier: Programming Language :: Python
Classifier: Programming Language :: Python :: 3
Classifier: Programming Language :: Python :: 3.12
Classifier: Programming Language :: Python :: 3.13
Classifier: Programming Language :: Python :: 3.14
Classifier: Intended Audience :: Developers
Classifier: Natural Language :: English
Classifier: Operating System :: POSIX
Classifier: Typing :: Typed
Requires-Python: >=3.12
License-File: LICENSE
Requires-Dist: Deprecated
Requires-Dist: IPython
Requires-Dist: pyvo
Requires-Dist: httpx
Requires-Dist: rubin-repertoire
Requires-Dist: pyyaml
Requires-Dist: structlog
Requires-Dist: symbolicmode
Requires-Dist: xmltodict
Dynamic: license-file
